altk/__init__.py
altk/aggregator.py
altk/filemanager.py
altk-0.0.2.dist-info/LICENSE.txt
altk-0.0.2.dist-info/METADATA
altk-0.0.2.dist-info/WHEEL
altk-0.0.2.dist-info/top_level.txt
altk-0.0.2.dist-info/RECORD
