Metadata-Version: 2.1
Name: altk
Version: 0.0.2
Summary: UNKNOWN
Home-page: https://github.com/ancient-lives/altk
Author: Alex Williams
Author-email: alex.williams@uwaterloo.ca
License: UNKNOWN
Keywords: ancient-lives
Platform: UNKNOWN
Classifier: Development Status :: 3 - Alpha
Classifier: Intended Audience :: Developers
Classifier: License :: OSI Approved :: MIT License
Classifier: Programming Language :: Python :: 2.6
Classifier: Programming Language :: Python :: 2.7
Classifier: Programming Language :: Python :: 3.6
Requires-Dist: tqdm (==4.28.1)
